bounding_shape/__init__.py
bounding_shape/bounding_shape.py
bounding_shape-0.2.1.dist-info/METADATA
bounding_shape-0.2.1.dist-info/WHEEL
bounding_shape-0.2.1.dist-info/licenses/LICENSE
bounding_shape-0.2.1.dist-info/RECORD
